{
   "class":[
      {
         "type_id":"甜圈",
         "type_name":"甜圈短剧"
      },
      {
         "type_id":"锦鲤",
         "type_name":"锦鲤短剧"
      },
      {
         "type_id":"番茄",
         "type_name":"番茄短剧"
      },
      {
         "type_id":"星芽",
         "type_name":"星芽短剧"
      },
      {
         "type_id":"西饭",
         "type_name":"西饭短剧"
      },
      {
         "type_id":"软鸭",
         "type_name":"软鸭短剧"
      },
      {
         "type_id":"七猫",
         "type_name":"七猫短剧"
      }
   ],
   "type":"聚合短剧",
   "filters":{
      "甜圈":[
         {
            "key":"area",
            "name":"剧情",
            "value":[
               {
                  "n":"全部",
                  "v":""
               },
               {
                  "n":"推荐榜",
                  "v":"推荐榜"
               },
               {
                  "n":"新剧",
                  "v":"新剧"
               },
               {
                  "n":"逆袭",
                  "v":"逆袭"
               },
               {
                  "n":"霸总",
                  "v":"霸总"
               },
               {
                  "n":"现代言情",
                  "v":"现代言情"
               },
               {
                  "n":"打脸虐渣",
                  "v":"打脸虐渣"
               },
               {
                  "n":"豪门恩怨",
                  "v":"豪门恩怨"
               },
               {
                  "n":"神豪",
                  "v":"神豪"
               },
               {
                  "n":"马甲",
                  "v":"马甲"
               },
               {
                  "n":"都市日常",
                  "v":"都市日常"
               },
               {
                  "n":"战神归来",
                  "v":"战神归来"
               },
               {
                  "n":"小人物",
                  "v":"小人物"
               },
               {
                  "n":"女性成长",
                  "v":"女性成长"
               },
               {
                  "n":"大女主",
                  "v":"大女主"
               },
               {
                  "n":"穿越",
                  "v":"穿越"
               },
               {
                  "n":"都市修仙",
                  "v":"都市修仙"
               },
               {
                  "n":"强者回归",
                  "v":"强者回归"
               },
               {
                  "n":"亲情",
                  "v":"亲情"
               },
               {
                  "n":"古装",
                  "v":"古装"
               },
               {
                  "n":"重生",
                  "v":"重生"
               },
               {
                  "n":"闪婚",
                  "v":"闪婚"
               },
               {
                  "n":"赘婿逆袭",
                  "v":"赘婿逆袭"
               },
               {
                  "n":"虐恋",
                  "v":"虐恋"
               },
               {
                  "n":"追妻",
                  "v":"追妻"
               },
               {
                  "n":"天下无敌",
                  "v":"天下无敌"
               },
               {
                  "n":"家庭伦理",
                  "v":"家庭伦理"
               },
               {
                  "n":"萌宝",
                  "v":"萌宝"
               },
               {
                  "n":"古风权谋",
                  "v":"古风权谋"
               },
               {
                  "n":"职场",
                  "v":"职场"
               },
               {
                  "n":"奇幻脑洞",
                  "v":"奇幻脑洞"
               },
               {
                  "n":"异能",
                  "v":"异能"
               },
               {
                  "n":"无敌神医",
                  "v":"无敌神医"
               },
               {
                  "n":"古风言情",
                  "v":"古风言情"
               },
               {
                  "n":"传承觉醒",
                  "v":"传承觉醒"
               },
               {
                  "n":"现言甜宠",
                  "v":"现言甜宠"
               },
               {
                  "n":"奇幻爱情",
                  "v":"奇幻爱情"
               },
               {
                  "n":"乡村",
                  "v":"乡村"
               },
               {
                  "n":"历史古代",
                  "v":"历史古代"
               },
               {
                  "n":"王妃",
                  "v":"王妃"
               },
               {
                  "n":"高手下山",
                  "v":"高手下山"
               },
               {
                  "n":"娱乐圈",
                  "v":"娱乐圈"
               },
               {
                  "n":"强强联合",
                  "v":"强强联合"
               },
               {
                  "n":"破镜重圆",
                  "v":"破镜重圆"
               },
               {
                  "n":"暗恋成真",
                  "v":"暗恋成真"
               },
               {
                  "n":"民国",
                  "v":"民国"
               },
               {
                  "n":"欢喜冤家",
                  "v":"欢喜冤家"
               },
               {
                  "n":"系统",
                  "v":"系统"
               },
               {
                  "n":"真假千金",
                  "v":"真假千金"
               },
               {
                  "n":"龙王",
                  "v":"龙王"
               },
               {
                  "n":"校园",
                  "v":"校园"
               },
               {
                  "n":"穿书",
                  "v":"穿书"
               },
               {
                  "n":"女帝",
                  "v":"女帝"
               },
               {
                  "n":"团宠",
                  "v":"团宠"
               },
               {
                  "n":"年代爱情",
                  "v":"年代爱情"
               },
               {
                  "n":"玄幻仙侠",
                  "v":"玄幻仙侠"
               },
               {
                  "n":"青梅竹马",
                  "v":"青梅竹马"
               },
               {
                  "n":"悬疑推理",
                  "v":"悬疑推理"
               },
               {
                  "n":"皇后",
                  "v":"皇后"
               },
               {
                  "n":"替身",
                  "v":"替身"
               },
               {
                  "n":"大叔",
                  "v":"大叔"
               },
               {
                  "n":"喜剧",
                  "v":"喜剧"
               },
               {
                  "n":"剧情",
                  "v":"剧情"
               }
            ]
         }
      ],
      "锦鲤":[
         {
            "key":"area",
            "name":"分类",
            "value":[
               {
                  "n":"全部",
                  "v":""
               },
               {
                  "n":"情感关系",
                  "v":"1"
               },
               {
                  "n":"成长逆袭",
                  "v":"2"
               },
               {
                  "n":"奇幻异能",
                  "v":"3"
               },
               {
                  "n":"战斗热血",
                  "v":"4"
               },
               {
                  "n":"伦理现实",
                  "v":"5"
               },
               {
                  "n":"时空穿越",
                  "v":"6"
               },
               {
                  "n":"权谋身份",
                  "v":"7"
               }
            ]
         }
      ],
      "番茄":[
         {
            "key":"area",
            "name":"分类",
            "value":[
               {
                  "n":"热剧",
                  "v":"videoseries_hot"
               },
               {
                  "n":"新剧",
                  "v":"firstonlinetime_new"
               },
               {
                  "n":"逆袭",
                  "v":"cate_739"
               },
               {
                  "n":"总裁",
                  "v":"cate_29"
               },
               {
                  "n":"现言",
                  "v":"cate_3"
               },
               {
                  "n":"打脸",
                  "v":"cate_1051"
               },
               {
                  "n":"马甲",
                  "v":"cate_266"
               },
               {
                  "n":"豪门",
                  "v":"cate_1053"
               },
               {
                  "n":"都市",
                  "v":"cate_261"
               },
               {
                  "n":"神豪",
                  "v":"cate_20"
               }
            ]
         }
      ],
      "星芽":[
         {
            "key":"area",
            "name":"分类",
            "value":[
               {
                  "n":"剧场",
                  "v":"1"
               },
               {
                  "n":"热播剧",
                  "v":"2"
               },
               {
                  "n":"会员专享",
                  "v":"8"
               },
               {
                  "n":"星选好剧",
                  "v":"7"
               },
               {
                  "n":"新剧",
                  "v":"3"
               },
               {
                  "n":"阳光剧场",
                  "v":"5"
               }
            ]
         }
      ],
      "西饭":[
         {
            "key":"area",
            "name":"分类",
            "value":[
               {
                  "n":"全部",
                  "v":""
               },
               {
                  "n":"都市",
                  "v":"68@都市"
               },
               {
                  "n":"青春",
                  "v":"68@青春"
               },
               {
                  "n":"现代言情",
                  "v":"81@现代言情"
               },
               {
                  "n":"豪门",
                  "v":"81@豪门"
               },
               {
                  "n":"大女主",
                  "v":"80@大女主"
               },
               {
                  "n":"逆袭",
                  "v":"79@逆袭"
               },
               {
                  "n":"打脸虐渣",
                  "v":"79@打脸虐渣"
               },
               {
                  "n":"穿越",
                  "v":"81@穿越"
               }
            ]
         }
      ],
      "软鸭":[
         {
            "key":"area",
            "name":"分类",
            "value":[
               {
                  "n":"战神",
                  "v":"战神"
               },
               {
                  "n":"逆袭",
                  "v":"逆袭"
               },
               {
                  "n":"人物",
                  "v":"人物"
               },
               {
                  "n":"都市",
                  "v":"都市"
               },
               {
                  "n":"擦边",
                  "v":"擦边"
               },
               {
                  "n":"人妖",
                  "v":"人妖"
               },
               {
                  "n":"闪婚",
                  "v":"闪婚"
               },
               {
                  "n":"古装",
                  "v":"古装"
               },
               {
                  "n":"霸总",
                  "v":"霸总"
               },
               {
                  "n":"强者",
                  "v":"强者"
               },
               {
                  "n":"玄幻",
                  "v":"玄幻"
               },
               {
                  "n":"神豪",
                  "v":"神豪"
               },
               {
                  "n":"现代",
                  "v":"现代"
               },
               {
                  "n":"爱情",
                  "v":"爱情"
               },
               {
                  "n":"虐渣",
                  "v":"虐渣"
               },
               {
                  "n":"总裁",
                  "v":"总裁"
               },
               {
                  "n":"无敌",
                  "v":"无敌"
               },
               {
                  "n":"奇幻",
                  "v":"奇幻"
               }
            ]
         }
      ],
      "七猫":[
         {
            "key":"area",
            "name":"分类",
            "value":[
               {
                  "n":"全部",
                  "v":""
               },
               {
                  "n":"推荐",
                  "v":"0"
               },
               {
                  "n":"新剧",
                  "v":"-1"
               },
               {
                  "n":"都市情感",
                  "v":"1273"
               },
               {
                  "n":"古装",
                  "v":"1272"
               },
               {
                  "n":"都市",
                  "v":"571"
               },
               {
                  "n":"玄幻仙侠",
                  "v":"1286"
               },
               {
                  "n":"奇幻",
                  "v":"570"
               },
               {
                  "n":"乡村",
                  "v":"590"
               },
               {
                  "n":"民国",
                  "v":"573"
               },
               {
                  "n":"年代",
                  "v":"572"
               },
               {
                  "n":"青春校园",
                  "v":"1288"
               },
               {
                  "n":"武侠",
                  "v":"371"
               },
               {
                  "n":"科幻",
                  "v":"594"
               },
               {
                  "n":"末世",
                  "v":"556"
               },
               {
                  "n":"二次元",
                  "v":"1289"
               },
               {
                  "n":"逆袭",
                  "v":"400"
               },
               {
                  "n":"穿越",
                  "v":"373"
               },
               {
                  "n":"复仇",
                  "v":"795"
               },
               {
                  "n":"系统",
                  "v":"787"
               },
               {
                  "n":"权谋",
                  "v":"790"
               },
               {
                  "n":"重生",
                  "v":"784"
               },
               {
                  "n":"女性成长",
                  "v":"1294"
               },
               {
                  "n":"打脸虐渣",
                  "v":"716"
               },
               {
                  "n":"闪婚",
                  "v":"480"
               },
               {
                  "n":"强者回归",
                  "v":"402"
               },
               {
                  "n":"追妻火葬场",
                  "v":"715"
               },
               {
                  "n":"家庭",
                  "v":"670"
               },
               {
                  "n":"马甲",
                  "v":"558"
               },
               {
                  "n":"职场",
                  "v":"724"
               },
               {
                  "n":"宫斗",
                  "v":"343"
               },
               {
                  "n":"高手下山",
                  "v":"1299"
               },
               {
                  "n":"娱乐明星",
                  "v":"1295"
               },
               {
                  "n":"异能",
                  "v":"727"
               },
               {
                  "n":"宅斗",
                  "v":"342"
               },
               {
                  "n":"替身",
                  "v":"712"
               },
               {
                  "n":"穿书",
                  "v":"338"
               },
               {
                  "n":"商战",
                  "v":"723"
               },
               {
                  "n":"种田经商",
                  "v":"1291"
               },
               {
                  "n":"伦理",
                  "v":"1293"
               },
               {
                  "n":"社会话题",
                  "v":"1290"
               },
               {
                  "n":"致富",
                  "v":"492"
               },
               {
                  "n":"偷听心声",
                  "v":"1258"
               },
               {
                  "n":"脑洞",
                  "v":"526"
               },
               {
                  "n":"豪门总裁",
                  "v":"624"
               },
               {
                  "n":"萌宝",
                  "v":"356"
               },
               {
                  "n":"战神",
                  "v":"527"
               },
               {
                  "n":"真假千金",
                  "v":"812"
               },
               {
                  "n":"赘婿",
                  "v":"36"
               },
               {
                  "n":"神医",
                  "v":"1269"
               },
               {
                  "n":"神豪",
                  "v":"37"
               },
               {
                  "n":"小人物",
                  "v":"1296"
               },
               {
                  "n":"团宠",
                  "v":"545"
               },
               {
                  "n":"欢喜冤家",
                  "v":"464"
               },
               {
                  "n":"女帝",
                  "v":"617"
               },
               {
                  "n":"银发",
                  "v":"1297"
               },
               {
                  "n":"兵王",
                  "v":"28"
               },
               {
                  "n":"虐恋",
                  "v":"16"
               },
               {
                  "n":"甜宠",
                  "v":"21"
               },
               {
                  "n":"悬疑",
                  "v":"27"
               },
               {
                  "n":"搞笑",
                  "v":"793"
               },
               {
                  "n":"灵异",
                  "v":"1287"
               }
            ]
         }
      ],
      "牛牛":[
         {
            "key":"area",
            "name":"分类",
            "value":[
               {
                  "n":"全部",
                  "v":""
               },
               {
                  "n":"现言",
                  "v":"现言"
               },
               {
                  "n":"古言",
                  "v":"古言"
               },
               {
                  "n":"历史",
                  "v":"历史"
               },
               {
                  "n":"都市",
                  "v":"都市"
               },
               {
                  "n":"活动",
                  "v":"活动"
               },
               {
                  "n":"逆袭",
                  "v":"逆袭"
               },
               {
                  "n":"豪门",
                  "v":"豪门"
               },
               {
                  "n":"战神",
                  "v":"战神"
               },
               {
                  "n":"甜宠",
                  "v":"甜宠"
               },
               {
                  "n":"穿越",
                  "v":"穿越"
               },
               {
                  "n":"古装",
                  "v":"古装"
               },
               {
                  "n":"虐心",
                  "v":"虐心"
               },
               {
                  "n":"神医",
                  "v":"神医"
               },
               {
                  "n":"赘婿",
                  "v":"赘婿"
               },
               {
                  "n":"亲情",
                  "v":"亲情"
               },
               {
                  "n":"复仇",
                  "v":"复仇"
               },
               {
                  "n":"玄幻",
                  "v":"玄幻"
               },
               {
                  "n":"热血",
                  "v":"热血"
               },
               {
                  "n":"动作",
                  "v":"动作"
               },
               {
                  "n":"喜剧",
                  "v":"喜剧"
               },
               {
                  "n":"悬疑",
                  "v":"悬疑"
               },
               {
                  "n":"军事",
                  "v":"军事"
               },
               {
                  "n":"二次元",
                  "v":"二次元"
               },
               {
                  "n":"未来",
                  "v":"未来"
               },
               {
                  "n":"快速穿越",
                  "v":"快速穿越"
               },
               {
                  "n":"烧脑",
                  "v":"烧脑"
               },
               {
                  "n":"治愈",
                  "v":"治愈"
               },
               {
                  "n":"其他剧情",
                  "v":"其他剧情"
               }
            ]
         }
      ]
   },
   "list":[
      {
         "vod_id":"软鸭@%E7%A6%81%E6%AD%A6%E4%B9%8B%E6%88%98%40https%3A%2F%2Fp3-reading-sign.fqnovelpic.com%2Fnovel-pic%2F3e002e03fb375ed87b226b3cdb5537ba~tplv-snk2bdmkp8-super-reso-double-5-v2%3A1200%3A0.image%3Flk3s%3Dae45642e%26x-expires%3D1765264941%26x-signature%3DH1rv%252FM%252BGUXVXf35EV9wPcewUSvM%253D%40%E7%9F%B3%E5%BB%BA%E6%98%8E%2C%E5%8F%B6%E5%A8%87%40%E9%83%BD%E5%B8%82%E8%84%91%E6%B4%9E%C2%B7%E9%83%BD%E5%B8%82%C2%B7%E5%85%A860%E9%9B%86%40%E9%9A%90%E9%80%80%E7%9A%84%E5%89%8D%E6%AD%A6%E6%9E%97%E7%9B%9F%E4%B8%BB%E7%9F%B3%E5%BB%BA%E6%98%8E%EF%BC%88%E7%9F%B3%E9%BB%91%E9%BE%99%EF%BC%89%E4%B8%8E%E5%8F%B6%E5%A8%87%E8%BF%87%E7%9D%80%E5%B9%B3%E5%87%A1%E7%94%9F%E6%B4%BB%EF%BC%8C%E5%8D%B4%E5%9B%A0%E5%AF%92%E5%B1%B1%E6%B4%BE%E5%B0%81%E4%B8%80%E5%AF%92%E6%AF%8D%E5%AD%90%E5%AF%BB%E4%BB%87%E6%89%93%E7%A0%B4%E5%B9%B3%E9%9D%99%E3%80%82%E7%A5%9E%E9%9A%90%E5%B1%80%E5%BC%82%E8%83%BD%E8%80%85%E4%B9%9F%E5%80%9F%E6%9C%BA%E6%89%93%E5%8E%8B%E6%AD%A6%E8%80%85%EF%BC%8C%E7%9F%B3%E5%BB%BA%E6%98%8E%E8%A2%AB%E8%BF%AB%E5%B1%95%E9%9C%B2%E8%BA%AB%E6%89%8B%E3%80%82%E4%BB%96%E5%9C%A8%E4%B8%8E%E5%B0%81%E5%AE%B6%E6%AF%8D%E5%AD%90%E3%80%81%E7%A5%9E%E9%9A%90%E5%B1%80%E7%99%BD%E5%A4%9C%E3%80%81%E8%B5%B5%E5%A4%A9%E9%9A%90%E5%8F%8A%E5%90%8E%E7%BB%AD%E7%87%95%E5%BD%92%E5%B0%98%E7%AD%89%E7%9A%84%E6%BF%80%E6%88%98%E4%B8%AD%EF%BC%8C%E6%8F%AD%E9%9C%B2%E5%90%84%E6%96%B9%E9%98%B4%E8%B0%8B%EF%BC%8C%E6%9C%80%E7%BB%88%E5%87%BB%E8%B4%A5%E5%90%B8%E6%94%B6%E5%85%B6%E5%BC%82%E8%83%BD%E7%9A%84%E7%87%95%E5%BD%92%E5%B0%98%E3%80%82%E9%A3%8E%E6%B3%A2%E8%BF%87%E5%90%8E%EF%BC%8C%E4%BB%96%E4%BB%8D%E6%B8%B4%E6%9C%9B%E4%B8%8E%E5%AE%B6%E4%BA%BA%E8%BF%87%E5%B9%B3%E9%9D%99%E7%94%9F%E6%B4%BB%E3%80%82%407553854659501247513",
         "vod_name":"禁武之战",
         "vod_remarks":"软鸭短剧 | 都市脑洞·都市·全60集",
         "vod_content":"",
         "vod_pic":"https://p3-reading-sign.fqnovelpic.com/novel-pic/3e002e03fb375ed87b226b3cdb5537ba~tplv-snk2bdmkp8-super-reso-double-5-v2:1200:0.image?lk3s=ae45642e&x-expires=1765264941&x-signature=H1rv%2FM%2BGUXVXf35EV9wPcewUSvM%3D",
         "vod_year":"未知"
      },
      {
         "vod_id":"软鸭@%E4%BA%BA%E4%B8%AD%E4%B9%8B%E9%BE%99%40https%3A%2F%2Fp3-reading-sign.fqnovelpic.com%2Fnovel-pic%2F6bafda20f0e65dd682f0837cd6430e92~tplv-snk2bdmkp8-super-reso-double-5-v2%3A1200%3A0.image%3Flk3s%3Dae45642e%26x-expires%3D1765264941%26x-signature%3D%252FFlqTlhK5RwxhR73XQykpnUCNcs%253D%40%E6%9D%8E%E4%BA%91%E4%B8%8A%2C%E7%87%95%E9%9B%AA%E6%9F%94%40%E6%88%98%E7%A5%9E%E5%BD%92%E6%9D%A5%C2%B7%E9%83%BD%E5%B8%82%C2%B7%E5%85%A881%E9%9B%86%40%E6%9D%8E%E6%97%A0%E5%8F%8C%E8%BA%AB%E4%B8%BA%E6%8A%A4%E9%BE%99%E9%98%81%E5%89%91%E5%B0%8A%EF%BC%8C%E5%A4%A9%E4%B8%8B%E9%97%BB%E5%90%8D%EF%BC%8C%E5%8D%B4%E5%8F%AA%E6%83%B3%E5%BD%92%E9%9A%90%E4%B9%A1%E4%B8%8B%EF%BC%8C%E9%99%AA%E4%BC%B4%E5%AE%B6%E4%BA%BA%EF%BC%8C%E4%BC%A0%E9%97%BB%E9%94%A6%E9%B2%A4%E5%B1%B1%E9%92%93%E9%94%A6%E9%B2%A4%EF%BC%8C%E9%94%A6%E9%B2%A4%E5%9C%A8%E6%89%8B%EF%BC%8C%E9%B8%BF%E8%BF%90%E5%BD%93%E5%A4%B4%EF%BC%8C%E5%BD%93%E6%9D%8E%E6%97%A0%E5%8F%8C%E9%92%93%E5%88%B0%E9%94%A6%E9%B2%A4%E6%97%B6%EF%BC%8C%E4%B8%80%E4%BC%99%E5%9C%B0%E7%97%9E%E5%8D%B4%E6%83%B3%E5%BC%BA%E6%8A%A2%EF%BC%8C%E6%BF%80%E6%80%92%E6%9D%8E%E6%97%A0%E5%8F%8C%EF%BC%8C%E5%A4%A7%E6%89%93%E5%87%BA%E6%89%8B%EF%BC%8C%E7%94%9A%E8%87%B3%E6%83%8A%E5%8A%A8%E4%BA%86%E4%B8%8A%E4%BA%AC%E7%AC%AC%E4%B8%80%E8%B1%AA%E9%97%A8%E7%87%95%E5%AE%B6%E5%A4%A7%E5%B0%8F%E5%A7%90%E5%89%8D%E6%9D%A5%E5%B8%AE%E5%BF%99%EF%BC%81%E6%9D%8E%E6%97%A0%E5%8F%8C%E5%92%8C%E7%87%95%E5%A4%A7%E5%B0%8F%E5%A7%90%E5%88%9A%E8%A7%A3%E5%86%B3%E5%9C%B0%E7%97%9E%EF%BC%8C%E6%9D%8E%E6%97%A0%E5%8F%8C%E5%B0%B1%E6%8E%A5%E5%88%B0%E4%BA%86%E5%A6%B9%E5%A6%B9%E7%9A%84%E7%94%B5%E8%AF%9D%EF%BC%8C%E6%9C%89%E6%81%B6%E9%9C%B8%E5%9C%A8%E6%9D%91%E9%87%8C%E5%BB%BA%E5%BA%A6%E5%81%87%E6%9D%91%EF%BC%8C%E6%89%93%E4%BC%A4%E4%BA%86%E4%BB%96%E7%88%B8%E5%A6%88%EF%BC%8C%E8%8B%B1%E9%9B%84%E4%B8%80%E6%80%92%EF%BC%8C%E7%8E%8B%E8%80%85%E6%8B%94%E5%89%91%EF%BC%8C%E4%BA%94%E6%B9%96%E5%9B%9B%E6%B5%B7%E9%A3%8E%E4%BA%91%E5%8F%98%E8%89%B2%EF%BC%81%407373152632791125017",
         "vod_name":"人中之龙",
         "vod_remarks":"软鸭短剧 | 战神归来·都市·全81集",
         "vod_content":"",
         "vod_pic":"https://p3-reading-sign.fqnovelpic.com/novel-pic/6bafda20f0e65dd682f0837cd6430e92~tplv-snk2bdmkp8-super-reso-double-5-v2:1200:0.image?lk3s=ae45642e&x-expires=1765264941&x-signature=%2FFlqTlhK5RwxhR73XQykpnUCNcs%3D",
         "vod_year":"未知"
      },
      {
         "vod_id":"软鸭@%E5%BC%91%E7%A5%9E%40https%3A%2F%2Fp3-reading-sign.fqnovelpic.com%2Fnovel-pic%2Fae3cd23f29ce73e9f163fd0187c0d4bd~tplv-snk2bdmkp8-super-reso-double-5-v2%3A1200%3A0.image%3Flk3s%3Dae45642e%26x-expires%3D1765264941%26x-signature%3DFR4UYVObkgWjt09V%252BQ1PM1dD2PU%253D%40%E5%B0%81%E6%97%A0%E7%83%AC%2C%E6%9D%A8%E5%AE%B9%E5%AE%B9%40%E7%8E%84%E5%B9%BB%E4%BB%99%E4%BE%A0%C2%B7%E5%A5%B3%E6%80%A7%E6%88%90%E9%95%BF%C2%B7%E5%85%A850%E9%9B%86%40%E6%9C%AC%E4%BD%9C%E5%93%81%E6%94%B9%E7%BC%96%E8%87%AA%E7%9B%90%E8%A8%80%E6%95%85%E4%BA%8B%E3%80%8A%E5%BC%91%E7%A5%9E%E3%80%8B%EF%BC%8C%E4%BD%9C%E8%80%85%E2%80%9C%E4%BA%8C%E5%88%86%E4%B9%8B%E4%B8%80%E5%A4%A9%E7%A9%BA%E2%80%9D%E3%80%82%E9%AD%94%E7%A5%9E%E4%B8%BA%E9%80%BC%E5%87%BA%E7%A5%9E%E5%A5%B3%EF%BC%8C%E5%B1%A0%E6%9D%80%E4%BA%86%E6%9D%A8%E5%AE%B6%E6%9D%91%EF%BC%8C%E7%A5%9E%E5%A5%B3%E5%8D%B4%E5%9B%A0%E4%B8%BA%E7%88%B1%E9%AD%94%E7%A5%9E%EF%BC%8C%E4%B8%8D%E5%BF%8D%E5%BF%83%E6%9D%80%E4%BB%96%E3%80%82%E6%9D%A8%E5%AE%B9%E5%AE%B9%E6%8A%B1%E7%9D%80%E5%A8%98%E4%BA%B2%E7%9A%84%E5%B0%B8%E4%BD%93%EF%BC%8C%E7%BB%88%E4%BA%8E%E6%98%8E%E7%99%BD%EF%BC%8C%E5%9C%A8%E7%A5%9E%E9%AD%94%E7%9C%BC%E4%B8%AD%EF%BC%8C%E5%87%A1%E4%BA%BA%E5%A6%82%E8%9D%BC%E8%9A%81%E3%80%82%E4%BD%86%E6%9D%A8%E5%AE%B9%E5%AE%B9%E4%B8%8D%E8%AE%A4%E5%91%BD%EF%BC%8C%E5%A5%B9%E4%BB%A5%E8%BA%AB%E4%B8%BA%E9%A5%B5%EF%BC%8C%E7%94%98%E5%BD%93%E5%A4%8D%E6%B4%BB%E7%A5%9E%E5%A5%B3%E7%9A%84%E5%AE%B9%E5%99%A8%EF%BC%8C%E6%BD%9C%E5%85%A5%E9%AD%94%E7%A5%9E%E8%BA%AB%E8%BE%B9%E3%80%82%E5%A5%B9%E8%A6%81%E8%AF%81%E6%98%8E%EF%BC%8C%E5%87%A1%E4%BA%BA%E4%BA%A6%E5%8F%AF%E5%BC%91%E7%A5%9E%E3%80%82%407555469136680193049",
         "vod_name":"弑神",
         "vod_remarks":"软鸭短剧 | 玄幻仙侠·女性成长·全50集",
         "vod_content":"",
         "vod_pic":"https://p3-reading-sign.fqnovelpic.com/novel-pic/ae3cd23f29ce73e9f163fd0187c0d4bd~tplv-snk2bdmkp8-super-reso-double-5-v2:1200:0.image?lk3s=ae45642e&x-expires=1765264941&x-signature=FR4UYVObkgWjt09V%2BQ1PM1dD2PU%3D",
         "vod_year":"未知"
      },
      {
         "vod_id":"软鸭@%E9%BE%99%E5%9B%BD%E6%88%98%E7%A5%9E%E8%87%B3%E5%B0%8A%E5%A4%A9%E4%B8%8B%40https%3A%2F%2Fp3-reading-sign.fqnovelpic.com%2Fnovel-pic%2F2f70c054279c01f263da6e842005d75f~tplv-snk2bdmkp8-super-reso-double-5-v2%3A1200%3A0.image%3Flk3s%3Dae45642e%26x-expires%3D1765264941%26x-signature%3DimuPVEpf6se3kBnvzojHPYF0VBw%253D%40%E5%8F%B6%E5%90%9B%E4%B8%B4%2C%E8%8B%8F%E6%B8%85%E9%9B%AA%40%E6%88%98%E7%A5%9E%E5%BD%92%E6%9D%A5%C2%B7%E9%A9%AC%E7%94%B2%C2%B7%E5%85%A8102%E9%9B%86%40%E6%91%98%E6%98%9F%E6%8F%BD%E6%9C%88%E8%AE%B8%E5%A5%B9%E4%B8%80%E4%B8%96%E7%B9%81%E5%8D%8E%EF%BC%8C%E5%9B%9E%E5%BD%92%E5%B7%85%E5%B3%B0%E5%B8%B7%E6%88%91%E5%90%9B%E4%B8%B4%E5%A4%A9%E4%B8%8B%E3%80%82%0A%E5%96%9D%E6%9C%80%E7%83%88%E6%9C%80%E9%A6%99%E7%9A%84%E7%BE%8E%E9%85%92%EF%BC%8C%E7%81%AD%E6%9C%80%E7%8B%82%E6%9C%80%E9%9C%B8%E9%81%93%E7%9A%84%E5%AF%B9%E6%89%8B%EF%BC%8C%E5%A8%B6%E6%9C%80%E8%BE%A3%E6%9C%80%E9%9D%93%E7%9A%84%E4%BB%99%E5%A5%B3%EF%BC%8C%E6%88%98%E7%A5%9E%E5%87%BA%E5%B1%B1%E5%BD%92%E6%9D%A5%EF%BC%8C%E9%83%BD%E5%B8%82%E5%B0%86%E5%86%8D%E6%AC%A1%E6%83%8A%E5%A4%A9%E5%8A%A8%E5%9C%B0%EF%BC%81%407392107802304449561",
         "vod_name":"龙国战神至尊天下",
         "vod_remarks":"软鸭短剧 | 战神归来·马甲·全102集",
         "vod_content":"",
         "vod_pic":"https://p3-reading-sign.fqnovelpic.com/novel-pic/2f70c054279c01f263da6e842005d75f~tplv-snk2bdmkp8-super-reso-double-5-v2:1200:0.image?lk3s=ae45642e&x-expires=1765264941&x-signature=imuPVEpf6se3kBnvzojHPYF0VBw%3D",
         "vod_year":"未知"
      },
      {
         "vod_id":"软鸭@%E5%8C%97%E5%A2%83%E6%88%98%E7%A5%9E%E7%AC%AC2%E9%83%A8%40https%3A%2F%2Fp3-reading-sign.fqnovelpic.com%2Fnovel-pic%2F4d9720444564bb20863b60bb85103185~tplv-snk2bdmkp8-super-reso-double-5-v2%3A1200%3A0.image%3Flk3s%3Dae45642e%26x-expires%3D1765264941%26x-signature%3DnZoqmrWzq1QlDGnZgnpXkpLk1%252FY%253D%40%E7%99%BD%E4%B9%9D%E9%9C%84%2C%E6%96%B9%E5%AE%9B%E5%A6%82%40%E6%88%98%E7%A5%9E%E5%BD%92%E6%9D%A5%C2%B7%E9%83%BD%E5%B8%82%C2%B7%E5%85%A878%E9%9B%86%40%E7%99%BD%E4%B9%9D%E9%9C%84%E4%BA%94%E5%B9%B4%E5%89%8D%E4%B8%BA%E7%88%B1%E9%A1%B6%E7%BD%AA%EF%BC%8C%E7%8B%B1%E4%B8%AD%E4%BA%94%E5%B9%B4%E8%8E%B7%E5%BE%97%E7%9A%84%E6%9C%BA%E9%81%87%E4%BD%BF%E7%99%BD%E4%B9%9D%E9%9C%84%E5%A4%A9%E4%B8%8B%E6%97%A0%E5%8F%8C%EF%BC%8C%E5%87%BA%E7%8B%B1%E6%97%B6%E5%90%84%E8%B7%AF%E4%B8%96%E8%B1%AA%E5%89%8D%E6%9D%A5%E4%BA%A4%E5%A5%BD%EF%BC%8C%E4%BD%86%E4%BB%96%E5%8F%AA%E6%83%B3%E6%8A%A5%E7%AD%94%E6%81%A9%E6%83%85%E5%B1%A5%E8%A1%8C%E4%B8%8E%E6%96%B9%E5%AE%9B%E5%A6%82%E7%9A%84%E5%A9%9A%E7%BA%A6%EF%BC%8C%E5%8D%B4%E6%83%A8%E9%81%AD%E8%83%8C%E5%8F%9B%E3%80%82%E7%8B%82%E5%A6%84%E8%87%AA%E5%A4%A7%E7%9A%84%E6%96%B9%E5%AE%B6%E7%AD%89%E4%BA%BA%E5%9B%A0%E5%BD%93%E5%B9%B4%E4%B9%8B%E4%BA%8B%E5%AF%B9%E7%99%BD%E4%B9%9D%E9%9C%84%E6%AC%BA%E8%BE%B1%E6%89%93%E5%8E%8B%EF%BC%8C%E5%BF%83%E4%B8%AD%E7%9A%84%E6%83%85%E8%B0%8A%E4%B8%80%E6%AC%A1%E6%AC%A1%E8%A2%AB%E6%B6%88%E8%80%97%E5%AE%8C%EF%BC%8C%E7%99%BD%E4%B9%9D%E9%9C%84%E4%BA%AE%E5%87%BA%E8%BA%AB%E4%BB%BD%E4%B8%80%E6%AD%A5%E6%AD%A5%E6%89%93%E8%84%B8%E4%BC%97%E4%BA%BA%EF%BC%8C%E4%B9%9F%E5%8F%91%E7%8E%B0%E8%87%AA%E5%B7%B1%E5%BF%83%E5%BF%83%E5%BF%B5%E5%BF%B5%E8%A6%81%E6%8A%A5%E6%81%A9%E7%9A%84%E5%A5%B3%E5%AD%A9%E5%8F%A6%E6%9C%89%E5%85%B6%E4%BA%BA%E3%80%82%407428896824548674622",
         "vod_name":"北境战神第2部",
         "vod_remarks":"软鸭短剧 | 战神归来·都市·全78集",
         "vod_content":"",
         "vod_pic":"https://p3-reading-sign.fqnovelpic.com/novel-pic/4d9720444564bb20863b60bb85103185~tplv-snk2bdmkp8-super-reso-double-5-v2:1200:0.image?lk3s=ae45642e&x-expires=1765264941&x-signature=nZoqmrWzq1QlDGnZgnpXkpLk1%2FY%3D",
         "vod_year":"未知"
      },
      {
         "vod_id":"软鸭@%E5%BC%91%E7%A5%9E%40https%3A%2F%2Fp3-reading-sign.fqnovelpic.com%2Fnovel-pic%2F876c9e44c55f3560c0dd388f7c288f21~tplv-snk2bdmkp8-super-reso-double-5-v2%3A1200%3A0.image%3Flk3s%3Dae45642e%26x-expires%3D1765264941%26x-signature%3DnCojKtTkYGJzkZNZpJs66wA8gEg%253D%40%E6%9E%97%E5%B2%B3%2C%E6%B1%9F%E9%A3%9E%E7%87%95%40%E5%A5%87%E5%B9%BB%E8%84%91%E6%B4%9E%C2%B7%E7%A5%9E%E8%B1%AA%C2%B7%E5%85%A873%E9%9B%86%40%E7%9B%96%E4%B8%96%E5%A4%A9%E5%8C%BB%E6%9E%97%E5%B2%B3%E5%8C%BB%E6%9C%AF%E7%BB%9D%E4%BC%A6%EF%BC%8C%E4%BB%A5%E6%B0%94%E6%B2%BB%E4%BA%BA%EF%BC%8C%E4%BA%94%E5%B9%B4%E5%89%8D%EF%BC%8C%E7%94%A8%E4%BC%8F%E7%BE%B2%E4%B9%9D%E9%92%88%E6%95%91%E5%85%AB%E6%97%8F%E4%BA%8E%E5%8D%B1%E9%9A%BE%E4%B9%8B%E4%B8%AD%EF%BC%8C%E6%8C%AF%E5%85%B4%E4%B8%AD%E6%B5%B7%E3%80%82%E4%B8%8D%E6%96%99%EF%BC%8C%E5%8D%B4%E8%A2%AB%E6%B1%9F%E6%B0%8F%E5%8D%83%E9%87%91%E6%B1%9F%E9%A3%9E%E7%87%95%E6%89%80%E9%AA%97%EF%BC%8C%E9%94%99%E4%BB%98%E7%9C%9F%E7%88%B1%E3%80%82%E8%80%8C%E8%87%AA%E5%B7%B1%E7%9C%9F%E6%AD%A3%E7%9A%84%E6%95%91%E5%91%BD%E6%81%A9%E4%BA%BA%E4%B8%8E%E5%AD%A9%E5%AD%90%E7%9A%84%E4%BA%B2%E7%94%9F%E6%AF%8D%E4%BA%B2%E5%AE%8B%E8%94%B7%E8%96%87%E4%B8%BA%E5%AD%A9%E5%AD%90%E5%BF%8D%E6%B0%94%E5%90%9E%E5%A3%B0%E5%81%9A%E6%B1%9F%E5%AE%B6%E4%BB%86%E4%BA%BA%EF%BC%8C%E6%83%A8%E9%81%AD%E5%87%8C%E8%BE%B1%E3%80%82%E8%BF%99%E6%AC%A1%E4%BB%96%E5%BF%8D%E6%97%A0%E5%8F%AF%E5%BF%8D%EF%BC%8C%E7%A9%BF%E4%B8%8A%E5%A4%AA%E6%9E%81%E5%87%B0%E8%A2%8D%EF%BC%8C%E6%92%A4%E5%9B%9E%E4%B8%87%E4%BA%BF%E5%AE%B6%E4%BA%A7%EF%BC%8C%E5%86%B3%E5%AE%9A%E4%BA%B2%E6%89%8B%E5%B1%A0%E6%9D%80%E8%BF%99%E6%9D%A1%E7%9B%98%E6%97%8B%E5%9C%A8%E4%B8%AD%E6%B5%B7%E7%9A%84%E2%80%9C%E6%81%B6%E9%BE%99%E2%80%9D%E3%80%82%407378148129717111833",
         "vod_name":"弑神",
         "vod_remarks":"软鸭短剧 | 奇幻脑洞·神豪·全73集",
         "vod_content":"",
         "vod_pic":"https://p3-reading-sign.fqnovelpic.com/novel-pic/876c9e44c55f3560c0dd388f7c288f21~tplv-snk2bdmkp8-super-reso-double-5-v2:1200:0.image?lk3s=ae45642e&x-expires=1765264941&x-signature=nCojKtTkYGJzkZNZpJs66wA8gEg%3D",
         "vod_year":"未知"
      },
      {
         "vod_id":"软鸭@%E9%BE%99%E7%A5%9E%E6%AE%BF%E4%B8%BB%40https%3A%2F%2Fp3-reading-sign.fqnovelpic.com%2Fnovel-pic%2Fb16cb14f37eaec34aef13e44dac4481a~tplv-snk2bdmkp8-super-reso-double-5-v2%3A1200%3A0.image%3Flk3s%3Dae45642e%26x-expires%3D1765264941%26x-signature%3DW%252BcnsGJQ4LcP7QoKlY5fwSKJO0k%253D%40%E5%94%90%E6%98%8E%E7%9F%BE%2C%E5%86%AF%E5%AD%90%E6%B2%AB%40%E6%88%98%E7%A5%9E%E5%BD%92%E6%9D%A5%C2%B7%E9%83%BD%E5%B8%82%C2%B7%E5%85%A896%E9%9B%86%40%E5%94%90%E6%98%8E%E7%9F%BE%E6%9B%BE%E6%B7%B1%E9%99%B7%E7%BB%9D%E5%A2%83%EF%BC%8C%E5%8D%B4%E5%9C%A8%E7%94%9F%E6%AD%BB%E4%B8%80%E7%BA%BF%E9%97%B4%E5%A5%87%E8%BF%B9%E8%A7%89%E9%86%92%E7%A5%9E%E7%A7%98%E4%BC%A0%E6%89%BF%EF%BC%8C%E8%87%AA%E6%AD%A4%E8%B8%8F%E4%B8%8A%E9%80%86%E8%A2%AD%E4%B9%8B%E8%B7%AF%E3%80%82%E4%BB%96%E5%87%AD%E5%80%9F%E9%9D%9E%E5%87%A1%E6%99%BA%E6%85%A7%E4%B8%8E%E6%9E%9C%E6%95%A2%E9%AD%84%E5%8A%9B%EF%BC%8C%E4%B8%80%E6%89%8B%E5%88%9B%E7%AB%8B%E5%A8%81%E9%9C%87%E5%85%AB%E6%96%B9%E7%9A%84%E9%BE%99%E7%A5%9E%E6%AE%BF%EF%BC%8C%E7%9F%AD%E7%9F%AD%E4%B8%89%E5%B9%B4%E4%BE%BF%E5%B0%86%E7%BD%AA%E6%81%B6%E4%B9%8B%E5%9F%8E%E7%9A%84%E9%BB%91%E6%9A%97%E5%8A%BF%E5%8A%9B%E8%BF%9E%E6%A0%B9%E6%8B%94%E8%B5%B7%EF%BC%8C%E5%A3%B0%E5%90%8D%E8%BF%9C%E6%89%AC%E5%9B%9B%E6%B5%B7%E3%80%82%E7%84%B6%E8%80%8C%EF%BC%8C%E5%B0%B1%E5%9C%A8%E4%BB%96%E5%8A%9F%E6%88%90%E5%90%8D%E5%B0%B1%E4%B9%8B%E6%97%B6%EF%BC%8C%E4%BC%A0%E6%9D%A5%E6%95%91%E5%91%BD%E6%81%A9%E4%BA%BA%E5%86%AF%E5%AD%90%E6%B2%AB%E8%A2%AB%E4%BA%BA%E6%AC%BA%E8%BE%B1%E7%9A%84%E5%99%A9%E8%80%97%E3%80%82%E5%BE%80%E6%98%94%E6%81%A9%E6%83%85%E5%8E%86%E5%8E%86%E5%9C%A8%E7%9B%AE%EF%BC%8C%E6%84%A4%E6%80%92%E5%9C%A8%E4%BB%96%E5%BF%83%E4%B8%AD%E7%86%8A%E7%86%8A%E7%87%83%E7%83%A7%EF%BC%8C%E5%94%90%E6%98%8E%E7%9F%BE%E5%AE%9A%E8%A6%81%E8%AE%A9%E9%82%A3%E4%BA%9B%E6%9B%BE%E4%BC%A4%E5%AE%B3%E8%BF%87%E4%BB%96%E4%BB%AC%E7%9A%84%E4%BA%BA%E4%BB%98%E5%87%BA%E6%83%A8%E7%97%9B%E4%BB%A3%E4%BB%B7%EF%BC%8C%E5%9C%A8%E4%BB%96%E7%9A%84%E6%80%92%E7%81%AB%E4%B8%8B%EF%BC%8C%E6%97%A0%E4%BA%BA%E8%83%BD%E9%80%83%EF%BC%8C%E4%B8%80%E5%9C%BA%E6%83%8A%E5%BF%83%E5%8A%A8%E9%AD%84%E7%9A%84%E5%A4%8D%E4%BB%87%E9%A3%8E%E6%9A%B4%E5%8D%B3%E5%B0%86%E5%B8%AD%E5%8D%B7%E6%B5%B7%E5%B7%9E%E3%80%82%407452268168673758270",
         "vod_name":"龙神殿主",
         "vod_remarks":"软鸭短剧 | 战神归来·都市·全96集",
         "vod_content":"",
         "vod_pic":"https://p3-reading-sign.fqnovelpic.com/novel-pic/b16cb14f37eaec34aef13e44dac4481a~tplv-snk2bdmkp8-super-reso-double-5-v2:1200:0.image?lk3s=ae45642e&x-expires=1765264941&x-signature=W%2BcnsGJQ4LcP7QoKlY5fwSKJO0k%3D",
         "vod_year":"未知"
      },
      {
         "vod_id":"软鸭@%E6%88%98%E7%A5%9E%E5%87%BA%E7%8B%B1%40https%3A%2F%2Fp3-reading-sign.fqnovelpic.com%2Fnovel-pic%2Fd552e87ca31b061c5fec74c6e008e124~tplv-snk2bdmkp8-super-reso-double-5-v2%3A1200%3A0.image%3Flk3s%3Dae45642e%26x-expires%3D1765264941%26x-signature%3DiKfyjFE5NpLwrdKzByKCfOk7y3E%253D%40%E8%90%A7%E6%88%98%2C%E8%8B%8F%E6%85%95%E7%A7%8B%40%E6%88%98%E7%A5%9E%E5%BD%92%E6%9D%A5%C2%B7%E9%83%BD%E5%B8%82%C2%B7%E5%85%A8101%E9%9B%86%40%E8%90%A7%E6%88%98%E5%9B%A0%E8%A2%AB%E4%BA%BA%E8%AF%AC%E9%99%B7%E5%85%A5%E7%8B%B1%E4%BA%94%E5%B9%B4%EF%BC%8C%E7%84%B6%E8%80%8C%E5%9C%A8%E7%8B%B1%E4%B8%AD%E4%BB%96%E7%A7%98%E5%AF%86%E6%88%90%E4%B8%BA%E4%BA%86%E5%8C%97%E5%A2%83%E7%8B%BC%E7%8E%8B%E3%80%82%E5%87%BA%E7%8B%B1%E4%B9%8B%E6%97%B6%EF%BC%8C%E8%90%A7%E5%AE%B6%E5%A6%84%E5%9B%BE%E7%BB%A7%E7%BB%AD%E5%8A%A0%E5%AE%B3%E8%90%A7%E6%88%98%EF%BC%8C%E4%BD%86%E8%90%A7%E6%88%98%E5%87%AD%E5%80%9F%E5%BC%BA%E5%A4%A7%E7%9A%84%E5%AE%9E%E5%8A%9B%E5%B0%86%E5%85%B6%E5%87%BB%E8%B4%A5%EF%BC%8C%E4%B9%9F%E8%AE%A9%E8%90%A7%E6%88%98%E5%9B%9E%E5%BF%86%E8%B5%B7%E6%AF%8D%E4%BA%B2%E6%AD%A3%E6%98%AF%E8%A2%AB%E8%90%A7%E5%AE%B6%E5%AE%B3%E6%AD%BB%EF%BC%8C%E5%A4%8D%E4%BB%87%E4%B9%8B%E8%B7%AF%E7%94%B1%E6%AD%A4%E5%BC%80%E5%A7%8B%E3%80%82%E5%90%8C%E6%97%B6%E8%90%A7%E6%88%98%E5%8F%91%E7%8E%B0%E6%9B%BE%E8%A2%AB%E4%B8%8B%E8%8D%AF%E7%9A%84%E8%8B%8F%E6%B2%90%E7%A7%8B%E4%B8%BA%E8%87%AA%E5%B7%B1%E7%94%9F%E4%B8%8B%E4%B8%80%E5%A5%B3%EF%BC%8C%E5%B9%B6%E4%B8%94%E5%9C%A8%E4%BB%96%E4%B8%8D%E7%9F%A5%E6%83%85%E7%9A%84%E6%83%85%E5%86%B5%E4%B8%8B%EF%BC%8C%E8%8B%8F%E6%B2%90%E7%A7%8B%E8%A2%AB%E8%83%81%E8%BF%AB%E8%A6%81%E5%AB%81%E7%BB%99%E4%B8%80%E4%B8%AA%E5%BC%BA%E5%A5%B8%E7%8A%AF%E3%80%82%E8%90%A7%E6%88%98%E8%87%AA%E7%84%B6%E4%B8%8D%E4%BC%9A%E5%85%81%E8%AE%B8%E8%BF%99%E6%A0%B7%E7%9A%84%E4%BA%8B%E6%83%85%E5%8F%91%E7%94%9F%EF%BC%8C%E4%BA%8E%E6%98%AF%E8%AE%A1%E5%88%92%E4%B8%8E%E8%8B%8F%E6%B2%90%E7%A7%8B%E7%BB%93%E5%A9%9A%EF%BC%8C%E5%AE%88%E6%8A%A4%E8%87%AA%E5%B7%B1%E7%9A%84%E7%88%B1%E4%BA%BA%E4%B8%8E%E5%A5%B3%E5%84%BF%E3%80%82%407414332419588754457",
         "vod_name":"战神出狱",
         "vod_remarks":"软鸭短剧 | 战神归来·都市·全101集",
         "vod_content":"",
         "vod_pic":"https://p3-reading-sign.fqnovelpic.com/novel-pic/d552e87ca31b061c5fec74c6e008e124~tplv-snk2bdmkp8-super-reso-double-5-v2:1200:0.image?lk3s=ae45642e&x-expires=1765264941&x-signature=iKfyjFE5NpLwrdKzByKCfOk7y3E%3D",
         "vod_year":"未知"
      },
      {
         "vod_id":"软鸭@%E5%BC%80%E5%B1%80%E8%BF%8E%E5%A8%B6%E5%A5%B3%E6%88%98%E7%A5%9E%EF%BC%8C%E5%8A%A9%E5%A5%B9%E7%A7%B0%E5%B8%9D%40https%3A%2F%2Fp3-reading-sign.fqnovelpic.com%2Fnovel-pic%2F5109dc25dca5008af391a4b26c6a6454~tplv-snk2bdmkp8-super-reso-double-5-v2%3A1200%3A0.image%3Flk3s%3Dae45642e%26x-expires%3D1765264941%26x-signature%3DF5bEME70s4B1vKjLkqj%252BQ9pJXSw%253D%40%E8%90%A7%E9%98%B3%2C%E5%AE%81%E7%BA%A2%E5%A4%9C%40%E5%A5%87%E5%B9%BB%E8%84%91%E6%B4%9E%C2%B7%E7%A9%BF%E8%B6%8A%C2%B7%E5%85%A880%E9%9B%86%40%E7%8E%B0%E4%BB%A3%E5%B0%8F%E4%BC%99%E8%90%A7%E9%98%B3%E6%84%8F%E5%A4%96%E7%A9%BF%E8%B6%8A%EF%BC%8C%E6%88%90%E4%BA%86%E9%95%87%E5%8C%97%E7%8E%8B%E5%BA%9C%E6%9C%80%E4%B8%8D%E5%8F%97%E5%AE%A0%E7%9A%84%E4%B9%9D%E4%B8%96%E5%AD%90%EF%BC%8C%E8%BF%98%E7%BB%91%E5%AE%9A%E4%BA%86%E4%B8%87%E5%80%8D%E8%BF%94%E8%BF%98%E7%B3%BB%E7%BB%9F%E3%80%82%E4%BB%96%E8%A2%AB%E8%BF%AB%E8%BF%8E%E5%A8%B6%E6%9C%89%E2%80%9C%E5%A5%B3%E6%9D%80%E7%A5%9E%E2%80%9D%E4%B9%8B%E7%A7%B0%E7%9A%84%E5%AE%81%E7%BA%A2%E5%A4%9C%E3%80%82%E8%90%A7%E9%98%B3%E5%88%A9%E7%94%A8%E7%B3%BB%E7%BB%9F%EF%BC%8C%E8%B5%A0%E4%BA%88%E5%AE%81%E7%BA%A2%E5%A4%9C%E7%81%B5%E7%9C%BC%E3%80%81%E5%AE%9D%E7%94%B2%E7%AD%89%EF%BC%8C%E6%94%B6%E8%8E%B7%E5%BC%BA%E5%8A%9B%E8%BF%94%E8%BF%98%E3%80%82%E6%9C%9F%E9%97%B4%EF%BC%8C%E4%BB%96%E5%B8%AE%E5%AE%81%E7%BA%A2%E5%A4%9C%E6%8F%AD%E5%BC%80%E5%BC%91%E7%88%B6%E7%9C%9F%E7%9B%B8%E3%80%82%E4%B9%8B%E5%90%8E%EF%BC%8C%E8%90%A7%E9%98%B3%E5%9C%A8%E7%8E%8B%E5%BA%9C%E5%85%84%E5%BC%9F%E4%BA%89%E6%96%97%E4%B8%AD%E8%83%9C%E5%87%BA%EF%BC%8C%E8%BE%85%E4%BD%90%E5%AE%81%E7%BA%A2%E5%A4%9C%E6%8E%A8%E7%BF%BB%E6%98%8F%E5%90%9B%EF%BC%8C%E5%8A%A9%E5%85%B6%E7%99%BB%E5%9F%BA%E4%B8%BA%E5%B8%9D%E3%80%82%E8%90%A7%E9%98%B3%E8%87%AA%E5%B7%B1%E5%88%99%E6%88%90%E4%B8%BA%E6%91%84%E6%94%BF%E7%8E%8B%EF%BC%8C%E4%B8%8E%E5%AE%81%E7%BA%A2%E5%A4%9C%E5%85%B1%E5%90%8C%E6%89%A7%E6%8E%8C%E5%A4%A7%E5%A4%8F%EF%BC%8C%E5%BC%80%E5%90%AF%E4%BA%86%E4%BA%8C%E4%BA%BA%E6%90%BA%E6%89%8B%E6%B2%BB%E4%B8%96%E7%9A%84%E6%96%B0%E7%AF%87%E7%AB%A0%E3%80%82%407549428429444090942",
         "vod_name":"开局迎娶女战神，助她称帝",
         "vod_remarks":"软鸭短剧 | 奇幻脑洞·穿越·全80集",
         "vod_content":"",
         "vod_pic":"https://p3-reading-sign.fqnovelpic.com/novel-pic/5109dc25dca5008af391a4b26c6a6454~tplv-snk2bdmkp8-super-reso-double-5-v2:1200:0.image?lk3s=ae45642e&x-expires=1765264941&x-signature=F5bEME70s4B1vKjLkqj%2BQ9pJXSw%3D",
         "vod_year":"未知"
      },
      {
         "vod_id":"软鸭@%E6%88%98%E7%A5%9E%20%E4%BB%A4%40https%3A%2F%2Fp3-reading-sign.fqnovelpic.com%2Fnovel-pic%2Fe49ed22012cfc4711533043d195e02bb~tplv-snk2bdmkp8-super-reso-double-5-v2%3A1200%3A0.image%3Flk3s%3Dae45642e%26x-expires%3D1765264941%26x-signature%3DXcqSfoxrFZV%252FJAvKpzmIzZNLE64%253D%40%E5%8F%B6%E5%B7%9D%2C%E5%86%B7%E6%A2%A6%40%E9%83%BD%E5%B8%82%E6%97%A5%E5%B8%B8%C2%B7%E9%83%BD%E5%B8%82%C2%B7%E5%85%A8237%E9%9B%86%40%E5%93%A5%E5%93%A5%E8%A2%AB%E5%A5%B8%E4%BA%BA%E6%89%80%E5%AE%B3%EF%BC%8C%E5%BC%9F%E5%BC%9F%E6%98%86%E4%BB%91%E6%AE%BF%E6%AE%BF%E4%B8%BB%E5%BE%97%E7%9F%A5%E5%90%8E%E6%8E%92%E9%99%A4%E4%B8%87%E9%99%A9%E5%AF%BB%E6%B1%82%E4%BA%8B%E6%83%85%E7%9A%84%E7%9C%9F%E7%9B%B8%EF%BC%8C%E5%B9%B6%E4%B8%80%E4%B8%80%E6%89%BE%E5%88%B0%E5%B9%95%E5%90%8E%E5%8F%82%E4%B8%8E%E8%80%85%E3%80%82%E6%9C%80%E7%BB%88%E5%87%AD%E5%80%9F%E5%AF%B9%E5%93%A5%E5%93%A5%E6%B7%B1%E5%8E%9A%E7%9A%84%E6%84%9F%E6%83%85%EF%BC%8C%E4%BB%A5%E5%8F%8A%E8%87%AA%E8%BA%AB%E5%BC%BA%E5%A4%A7%E7%9A%84%E8%83%8C%E6%99%AF%E5%92%8C%E5%AE%9E%E5%8A%9B%EF%BC%8C%E5%9C%A8%E8%B4%B4%E8%BA%AB%E4%BF%9D%E9%95%96%E7%AD%89%E4%BA%BA%E7%9A%84%E5%B8%AE%E5%8A%A9%E4%B8%8B%E4%B8%BA%E5%93%A5%E5%93%A5%E6%8A%A5%E4%BA%86%E4%BB%87%EF%BC%8C%E5%A4%9A%E6%AC%A1%E8%A7%A3%E6%95%91%E4%BA%86%E5%8F%97%E8%8B%A6%E5%8F%97%E9%9A%BE%E7%9A%84%E4%BE%84%E5%A5%B3%E5%92%8C%E5%AB%82%E5%AD%90%EF%BC%8C%E5%B0%86%E6%89%80%E6%9C%89%E5%9D%8F%E4%BA%BA%E7%BB%B3%E4%B9%8B%E4%BB%A5%E6%B3%95%E3%80%82%E6%9C%80%E5%90%8E%E4%B8%8E%E8%B4%B4%E8%BA%AB%E4%BF%9D%E9%95%96%E6%89%BE%E5%88%B0%E4%BA%86%E5%BD%BC%E6%AD%A4%E7%9A%84%E7%88%B1%E6%83%85%E3%80%82%407307531044264086569",
         "vod_name":"战神 令",
         "vod_remarks":"软鸭短剧 | 都市日常·都市·全237集",
         "vod_content":"",
         "vod_pic":"https://p3-reading-sign.fqnovelpic.com/novel-pic/e49ed22012cfc4711533043d195e02bb~tplv-snk2bdmkp8-super-reso-double-5-v2:1200:0.image?lk3s=ae45642e&x-expires=1765264941&x-signature=XcqSfoxrFZV%2FJAvKpzmIzZNLE64%3D",
         "vod_year":"未知"
      }
   ]
}